{
  "takenAt": "2026-07-03T21:21:16.564Z",
  "members": [
    {
      "id": "wmd3",
      "name": "Nicolas L",
      "rank": 1,
      "totalPoints": 508,
      "isAdmin": false
    },
    {
      "id": "8Yak",
      "name": "Cayan F",
      "rank": 2,
      "totalPoints": 484,
      "isAdmin": false
    },
    {
      "id": "9Nz1",
      "name": "Vitor Pinto",
      "rank": 3,
      "totalPoints": 469,
      "isAdmin": false
    },
    {
      "id": "7GjW",
      "name": "Mehdi M",
      "rank": 4,
      "totalPoints": 460,
      "isAdmin": true
    },
    {
      "id": "O52a",
      "name": "Joao M",
      "rank": 5,
      "totalPoints": 452,
      "isAdmin": false
    },
    {
      "id": "G3EG",
      "name": "Thomas M",
      "rank": 6,
      "totalPoints": 449,
      "isAdmin": false
    }
  ],
  "experts": []
}